shraddha/__init__.py
shraddha/__main__.py
shraddha/shraddha_demo.py
shraddha-1.0.2.dist-info/METADATA
shraddha-1.0.2.dist-info/WHEEL
shraddha-1.0.2.dist-info/top_level.txt
shraddha-1.0.2.dist-info/RECORD
