Metadata-Version: 2.1
Name: shraddha
Version: 1.0.2
Summary: Shraddhas test package
Home-page: https://github.com/shr1911/shraddha-pkg
Author: Shraddha Makwana
Author-email: smakwana@ualberta.ca
License: MIT
Requires-Python: >=3.6
